liiatools/__init__.py
liiatools/__main__.py
liiatools/common/__init__.py
liiatools/common/_fs_serializer.py
liiatools/common/_transform_functions.py
liiatools/common/archive.py
liiatools/common/data.py
liiatools/common/pipeline.py
liiatools/common/reference/__init__.py
liiatools/common/reference/_authorities.py
liiatools/common/reference/_authorities.yml
liiatools/common/stream_errors.py
liiatools/common/stream_filters.py
liiatools/common/transform.py
liiatools/datasets/__init__.py
liiatools/datasets/annex_a/README.md
liiatools/datasets/annex_a/__init__.py
liiatools/datasets/annex_a/annex_a_cli.py
liiatools/datasets/annex_a/lds_annexa_clean/__init__.py
liiatools/datasets/annex_a/lds_annexa_clean/cleaner.py
liiatools/datasets/annex_a/lds_annexa_clean/configuration.py
liiatools/datasets/annex_a/lds_annexa_clean/converters.py
liiatools/datasets/annex_a/lds_annexa_clean/degrade.py
liiatools/datasets/annex_a/lds_annexa_clean/file_creator.py
liiatools/datasets/annex_a/lds_annexa_clean/logger.py
liiatools/datasets/annex_a/lds_annexa_clean/populate.py
liiatools/datasets/annex_a/lds_annexa_clean/regex.py
liiatools/datasets/annex_a/lds_annexa_la_agg/__init__.py
liiatools/datasets/annex_a/lds_annexa_la_agg/configuration.py
liiatools/datasets/annex_a/lds_annexa_la_agg/process.py
liiatools/datasets/annex_a/lds_annexa_pan_agg/__init__.py
liiatools/datasets/annex_a/lds_annexa_pan_agg/configuration.py
liiatools/datasets/annex_a/lds_annexa_pan_agg/process.py
liiatools/datasets/cin_census/__init__.py
liiatools/datasets/cin_census/cin_cli.py
liiatools/datasets/cin_census/lds_cin_clean/__init__.py
liiatools/datasets/cin_census/lds_cin_clean/cin_record.py
liiatools/datasets/cin_census/lds_cin_clean/configuration.py
liiatools/datasets/cin_census/lds_cin_clean/converter.py
liiatools/datasets/cin_census/lds_cin_clean/file_creator.py
liiatools/datasets/cin_census/lds_cin_clean/filters.py
liiatools/datasets/cin_census/lds_cin_clean/logger.py
liiatools_dagster-0.2.0.dist-info/LICENSE
liiatools_dagster-0.2.0.dist-info/METADATA
liiatools_dagster-0.2.0.dist-info/WHEEL
liiatools_dagster-0.2.0.dist-info/RECORD
