Metadata-Version: 2.1
Name: liiatools-dagster
Version: 0.2.0
Summary: Children's Services Data Tools - Utilities for cleaning and normalising CS data by Social Finance
License: MIT
Author: Michael Hanks
Author-email: michael.hanks@socialfinance.org.uk
Requires-Python: >=3.9,<4.0
Classifier: License :: OSI Approved :: MIT License
Classifier: Programming Language :: Python :: 3
Classifier: Programming Language :: Python :: 3.9
Classifier: Programming Language :: Python :: 3.10
Classifier: Programming Language :: Python :: 3.11
Provides-Extra: s3
Requires-Dist: PyYAML (>=6.0,<7.0)
Requires-Dist: XlsxWriter (>=3.0.3,<4.0.0)
Requires-Dist: click (>=8.1.2,<9.0.0)
Requires-Dist: click-log (>=0.4.0,<0.5.0)
Requires-Dist: dacite (>=1.6.0,<2.0.0)
Requires-Dist: faust-cchardet (>=2.1.19,<3.0.0)
Requires-Dist: fs (>=2.4.16,<3.0.0)
Requires-Dist: fs-s3fs (>=1.1.1,<2.0.0) ; extra == "s3"
Requires-Dist: lxml (>=4.9.1,<5.0.0)
Requires-Dist: more-itertools (>=8.12.0,<9.0.0)
Requires-Dist: openpyxl (>=3.0.9,<4.0.0)
Requires-Dist: pandas (>=1.4.2,<2.0.0)
Requires-Dist: pyarrow (>=13.0.0,<14.0.0)
Requires-Dist: pydantic (<2.0.0)
Requires-Dist: pydantic-yaml (>=1.1.1,<2.0.0)
Requires-Dist: python-decouple (>=3.8,<4.0)
Requires-Dist: regex (>=2022.4.24,<2023.0.0)
Requires-Dist: sfdata-stream-parser (>=0.6.0,<0.7.0)
Requires-Dist: tablib[cli,xlsx] (>=3.2.0,<4.0.0)
Requires-Dist: xlrd (>=2.0.1,<3.0.0)
Requires-Dist: xmlschema (>=1.10.0,<2.0.0)
